setup.py
shinkenplugins/__init__.py
shinkenplugins.plugins.glance.egg-info/PKG-INFO
shinkenplugins.plugins.glance.egg-info/SOURCES.txt
shinkenplugins.plugins.glance.egg-info/dependency_links.txt
shinkenplugins.plugins.glance.egg-info/entry_points.txt
shinkenplugins.plugins.glance.egg-info/namespace_packages.txt
shinkenplugins.plugins.glance.egg-info/requires.txt
shinkenplugins.plugins.glance.egg-info/top_level.txt
shinkenplugins/plugins/__init__.py
shinkenplugins/plugins/glance/__init__.py
shinkenplugins/plugins/glance/glance.py