Metadata-Version: 1.0
Name: shinkenplugins.plugins.glance
Version: 1.0
Summary: A Shinken plugin to check the OpenStack Glance service
Home-page: https://github.com/savoirfairelinux/sfl-shinken-plugins
Author: Grégory Starck
Author-email: gregory.starck@savoirfairelinux.com
License: GPL3+
Platform: any
